pta_learn/__init__.py
pta_learn/bourdet_derivative.py
pta_learn/feature_extraction.py
pta_learn/lmir.py
pta_learn/normalization.py
pta_learn/pattern_recognition.py
pta_learn/superposition_calculation.py
pta_learn/ti_misc.py
pta_learn/ti_workflow.py
pta_learn/tpmr.py
pta_learn/utils.py
pta_learn-1.0.3.dist-info/METADATA
pta_learn-1.0.3.dist-info/WHEEL
pta_learn-1.0.3.dist-info/licenses/LICENSE
pta_learn-1.0.3.dist-info/RECORD
