Metadata-Version: 2.4
Name: pta-learn
Version: 1.0.3
Summary: A Python library for automated Pressure Transient Analysis (PTA) workflows. It provides tools for PTA flow regime feature extraction, time-lapse pattern recognition, pressure transient identification, and Bourdet derivative calculation.
Project-URL: Homepage, https://github.com/vitaliistarr/pta-learn
Project-URL: Repository, https://github.com/vitaliistarr/pta-learn.git
Project-URL: Bug Tracker, https://github.com/vitaliistarr/pta-learn/issues
Author-email: "V. Starikov" <starikovv98@gmail.com>, "B. Cui" <boyu.cui@qq.com>
License: MIT License
License-File: LICENSE
Keywords: Bourdet-derivative,feature-extraction,loglog-plot,pattern-recognition,pressure-transient-analysis,transient-identification,well-testing
Classifier: Development Status :: 4 - Beta
Classifier: Intended Audience :: Science/Research
Classifier: License :: OSI Approved :: MIT License
Classifier: Programming Language :: Python :: 3.12
Classifier: Topic :: Scientific/Engineering
Requires-Python: >=3.12
Requires-Dist: kneebow==1.0.1
Requires-Dist: matplotlib==3.10.1
Requires-Dist: numba>=0.61.0
Requires-Dist: numpy==2.1.3
Requires-Dist: pandas==2.2.3
Requires-Dist: plotly>=5.24.1
Requires-Dist: scikit-learn==1.6.1
Requires-Dist: scikit-optimize==0.10.2
Requires-Dist: scipy==1.15.0
Provides-Extra: dev
Requires-Dist: black>=22.0; extra == 'dev'
Requires-Dist: isort>=5.0; extra == 'dev'
Requires-Dist: pytest-cov>=2.0; extra == 'dev'
Requires-Dist: pytest>=6.0; extra == 'dev'
